adder/full_adder.vhd
LIBRARY ieee;
USE ieee.std_logic_1164.ALL;

ENTITY full_adder IS
    PORT (
        a, b : IN STD_LOGIC;
        ci : IN STD_LOGIC;
        co : OUT STD_LOGIC;
        s : OUT STD_LOGIC
    );
END ENTITY;

ARCHITECTURE arch OF full_adder IS
BEGIN
    s <= a XOR b XOR ci;
    co <= (a AND b) OR (a AND ci) OR (b AND ci);
END ARCHITECTURE;

adder/adder_4_bits.vhd
LIBRARY ieee;
USE ieee.std_logic_1164.ALL;

ENTITY adder_4_bits IS
    PORT (
        n1, n2 : IN STD_LOGIC_VECTOR(3 DOWNTO 0);
        ci : IN STD_LOGIC;
        co : OUT STD_LOGIC;
        output : OUT STD_LOGIC_VECTOR(3 DOWNTO 0)
    );
END ENTITY;

ARCHITECTURE arch OF adder_4_bits IS
    SIGNAL co2, co1, co0 : STD_LOGIC;
BEGIN
    adder_inst0 : ENTITY work.full_adder
        PORT MAP(
            a => n1(0),
            b => n2(0),
            ci => ci,
            co => co0,
            s => output(0)
        );

    adder_inst1 : ENTITY work.full_adder
        PORT MAP(
            a => n1(1),
            b => n2(1),
            ci => co0,
            co => co1,
            s => output(1)
        );

    adder_inst2 : ENTITY work.full_adder
        PORT MAP(
            a => n1(2),
            b => n2(2),
            ci => co1,
            co => co2,
            s => output(2)
        );

    adder_inst3 : ENTITY work.full_adder
        PORT MAP(
            a => n1(3),
            b => n2(3),
            ci => co2,
            co => co,
            s => output(3)
        );

END ARCHITECTURE;

adder/adder_sub.vhd
LIBRARY ieee;
USE ieee.std_logic_1164.ALL;
USE ieee.numeric_std.ALL;

ENTITY adder_sub IS
    PORT (
        n1, n2 : IN STD_LOGIC_VECTOR(3 DOWNTO 0);
        sub : IN STD_LOGIC;
        co : OUT STD_LOGIC;
        output : OUT STD_LOGIC_VECTOR(3 DOWNTO 0)
    );
END ENTITY;

ARCHITECTURE arch OF adder_sub IS
    SIGNAL p2 : STD_LOGIC_VECTOR(3 DOWNTO 0);
BEGIN

    p2 <= n2 WHEN sub = '0' ELSE
        NOT n2;

    adder_4_bits_inst : ENTITY work.adder_4_bits
        PORT MAP(
            n1 => n1,
            n2 => p2,
            ci => sub,
            co => co,
            output => output
        );

END ARCHITECTURE;

adder/top.vhd
LIBRARY ieee;
USE ieee.std_logic_1164.ALL;
USE ieee.numeric_std.ALL;

ENTITY top IS
END ENTITY;

ARCHITECTURE arch OF top IS
    SIGNAL co, sub : STD_LOGIC;
    SIGNAL n1, n2, output : STD_LOGIC_VECTOR(3 DOWNTO 0);
BEGIN

    adder_sub_inst : ENTITY work.adder_sub
        PORT MAP(
            n1 => n1,
            n2 => n2,
            sub => sub,
            co => co,
            output => output
        );

    PROCESS BEGIN

        sub <= '0';
        n1 <= "0000";
        n2 <= "0000";
        WAIT FOR 1 ns;

        sub <= '0';
        n1 <= "0001";
        n2 <= "0000";
        WAIT FOR 1 ns;

        sub <= '0';
        n1 <= "0001";
        n2 <= "0001";
        WAIT FOR 1 ns;

        sub <= '1';
        n1 <= "0001";
        n2 <= "0011";
        WAIT FOR 1 ns;

        sub <= '1';
        n1 <= "0100";
        n2 <= "0011";
        WAIT FOR 1 ns;

        sub <= '1';
        n2 <= "0010";
        n1 <= "0101";
        WAIT FOR 1 ns;

        sub <= '1';
        n1 <= "0101";
        n2 <= "1110";
        WAIT FOR 1 ns;

        sub <= '1';
        n1 <= "1111";
        n2 <= "1111";
        WAIT FOR 1 ns;

        ASSERT false REPORT "Reached end of test";
        WAIT;
    END PROCESS;
END ARCHITECTURE;

adder/wave.vcd
$date
  Sat May 13 19:30:09 2023
$end
$version
  GHDL v0
$end
$timescale
  1 fs
$end
$scope module standard $end
$upscope $end
$scope module std_logic_1164 $end
$upscope $end
$scope module numeric_std $end
$upscope $end
$scope module top $end
$var reg 1 ! co $end
$var reg 1 " sub $end
$var reg 4 # n1[3:0] $end
$var reg 4 $ n2[3:0] $end
$var reg 4 % output[3:0] $end
$scope module adder_sub_inst $end
$var reg 4 & n1[3:0] $end
$var reg 4 ' n2[3:0] $end
$var reg 1 ( sub $end
$var reg 1 ) co $end
$var reg 4 * output[3:0] $end
$var reg 4 + p2[3:0] $end
$scope module adder_4_bits_inst $end
$var reg 4 , n1[3:0] $end
$var reg 4 - n2[3:0] $end
$var reg 1 . ci $end
$var reg 1 / co $end
$var reg 4 0 output[3:0] $end
$var reg 1 1 co2 $end
$var reg 1 2 co1 $end
$var reg 1 3 co0 $end
$scope module adder_inst1 $end
$var reg 1 4 a $end
$var reg 1 5 b $end
$var reg 1 6 ci $end
$var reg 1 7 co $end
$var reg 1 8 s $end
$upscope $end
$scope module adder_inst2 $end
$var reg 1 9 a $end
$var reg 1 : b $end
$var reg 1 ; ci $end
$var reg 1 < co $end
$var reg 1 = s $end
$upscope $end
$scope module adder_inst3 $end
$var reg 1 > a $end
$var reg 1 ? b $end
$var reg 1 @ ci $end
$var reg 1 A co $end
$var reg 1 B s $end
$upscope $end
$scope module adder_inst4 $end
$var reg 1 C a $end
$var reg 1 D b $end
$var reg 1 E ci $end
$var reg 1 F co $end
$var reg 1 G s $end
$upscope $end
$upscope $end
$upscope $end
$upscope $end
$enddefinitions $end
#0
0!
0"
b0000 #
b0000 $
b0000 %
b0000 &
b0000 '
0(
0)
b0000 *
b0000 +
b0000 ,
b0000 -
0.
0/
b0000 0
01
02
03
04
05
06
07
08
09
0:
0;
0<
0=
0>
0?
0@
0A
0B
0C
0D
0E
0F
0G
#1000000
b0001 #
b0001 %
b0001 &
b0001 *
b0001 ,
b0001 0
14
18
#2000000
b0001 $
b0010 %
b0001 '
b0010 *
b0001 +
b0001 -
b0010 0
13
15
17
08
1;
1=
#3000000
1"
b0011 $
b1110 %
b0011 '
1(
b1110 *
b1100 +
b1100 -
1.
b1110 0
05
16
08
1?
1B
1D
1G
#4000000
1!
b0100 #
b0001 %
b0100 &
1)
b0001 *
b0100 ,
1/
b0001 0
11
03
04
07
18
0;
0=
1>
1A
0B
1E
1F
0G
#5000000
b0101 #
b0010 $
b0011 %
b0101 &
b0010 '
b0011 *
b1101 +
b0101 ,
b1101 -
b0011 0
13
14
15
17
18
1;
1=
#6000000
0!
b1110 $
b0111 %
b1110 '
0)
b0111 *
b0001 +
b0001 -
0/
b0111 0
01
0?
0A
1B
0D
0E
0F
0G
#7000000
1!
b1111 #
b1111 $
b0000 %
b1111 &
b1111 '
1)
b0000 *
b0000 +
b1111 ,
b0000 -
1/
b0000 0
11
12
05
08
19
1<
0=
1@
1A
0B
1C
1E
1F
0G
